NTQBOT/__init__.py
NTQBOT-1.0.0.dist-info/METADATA
NTQBOT-1.0.0.dist-info/WHEEL
NTQBOT-1.0.0.dist-info/top_level.txt
NTQBOT-1.0.0.dist-info/RECORD
