Metadata-Version: 2.1
Name: NTQBOT
Version: 1.0.0
Summary: The Best Fortnite LOBBYBOT with the latest features
Home-page: https://www.youtube.com/
Author: Mathyslol
Classifier: Programming Language :: Python :: 3
Classifier: License :: OSI Approved :: MIT License
Classifier: Operating System :: OS Independent
Requires-Dist: crayons
Requires-Dist: PirxcyPinger
Requires-Dist: fortnitepy
Requires-Dist: FortniteAPIAsync
Requires-Dist: sanic ==21.6.2
Requires-Dist: aiohttp
Requires-Dist: uvloop
Requires-Dist: requests
